geojson_faker/__init__.py
geojson_faker/constants.py
geojson_faker/faker.py
geojson_faker/generators.py
geojson_faker/types.py
geojson_faker-1.0.0.dist-info/METADATA
geojson_faker-1.0.0.dist-info/WHEEL
geojson_faker-1.0.0.dist-info/RECORD
