Metadata-Version: 2.1
Name: geojson-faker
Version: 1.0.0
Summary: GeoJson fake generator.
Home-page: https://github.com/impocode/geojson-faker
License: MIT
Keywords: geojson
Author: impocode
Author-email: impocode@impocode.one
Maintainer: impocode
Maintainer-email: impocode@impocode.one
Requires-Python: >=3.8.1,<4.0.0
Classifier: License :: OSI Approved :: MIT License
Classifier: Programming Language :: Python :: 3
Classifier: Programming Language :: Python :: 3.9
Classifier: Programming Language :: Python :: 3.10
Classifier: Programming Language :: Python :: 3.11
Classifier: Programming Language :: Python :: 3.12
Classifier: Programming Language :: Python :: 3 :: Only
Classifier: Programming Language :: Python :: 3.8
Requires-Dist: geojson-pydantic (>=1.1.0,<2.0.0)
Project-URL: Documentation, https://github.com/impocode/geojson-faker
Project-URL: Repository, https://github.com/impocode/geojson-faker
